django-allauth-steemconnect/__init__.py
django-allauth-steemconnect/providers/__init__.py
django-allauth-steemconnect/providers/steemconnect/__init__.py
django-allauth-steemconnect/providers/steemconnect/provider.py
django-allauth-steemconnect/providers/steemconnect/tests.py
django-allauth-steemconnect/providers/steemconnect/urls.py
django-allauth-steemconnect/providers/steemconnect/views.py
django-allauth-steemconnect/providers/steemconnect/__pycache__/__init__.cpython-37.pyc
django-allauth-steemconnect/providers/steemconnect/__pycache__/provider.cpython-37.pyc
django-allauth-steemconnect/providers/steemconnect/__pycache__/urls.cpython-37.pyc
django-allauth-steemconnect/providers/steemconnect/__pycache__/views.cpython-37.pyc
django_allauth_steemconnect/__init__.py
django_allauth_steemconnect/providers/__init__.py
django_allauth_steemconnect/providers/steemconnect/__init__.py
django_allauth_steemconnect/providers/steemconnect/provider.py
django_allauth_steemconnect/providers/steemconnect/tests.py
django_allauth_steemconnect/providers/steemconnect/urls.py
django_allauth_steemconnect/providers/steemconnect/views.py
django_allauth_steemconnect/providers/steemconnect/__pycache__/__init__.cpython-37.pyc
django_allauth_steemconnect/providers/steemconnect/__pycache__/provider.cpython-37.pyc
django_allauth_steemconnect/providers/steemconnect/__pycache__/urls.cpython-37.pyc
django_allauth_steemconnect/providers/steemconnect/__pycache__/views.cpython-37.pyc
django_allauth_steemconnect-0.1.2.dist-info/LICENSE
django_allauth_steemconnect-0.1.2.dist-info/METADATA
django_allauth_steemconnect-0.1.2.dist-info/WHEEL
django_allauth_steemconnect-0.1.2.dist-info/top_level.txt
django_allauth_steemconnect-0.1.2.dist-info/RECORD
